moore/__init__.py
moore/_version.py
moore/api.py
moore/const.py
moore/exception.py
moore/moore_data.py
moore/check/__init__.py
moore/check/check.py
moore/check/statistics.py
moore/export_format/__init__.py
moore/export_format/export.py
moore/export_format/coco/__init__.py
moore/export_format/coco/coco.py
moore/export_format/coco/export_coco.py
moore/export_format/kitti/__init__.py
moore/export_format/kitti/export_kitti.py
moore/export_format/kitti/kitti.py
moore/export_format/labelme/__init__.py
moore/export_format/labelme/export_labelme.py
moore/export_format/labelme/labelme.py
moore/export_format/mask/__init__.py
moore/export_format/mask/generate_mask.py
moore/export_format/voc/__init__.py
moore/export_format/voc/export_voc.py
moore/export_format/voc/voc.py
moore/export_format/yolo/__init__.py
moore/export_format/yolo/export_yolo.py
moore/export_format/yolo/yolo.py
moore/factory/__init__.py
moore/factory/data_factory.py
moore/post_process/__init__.py
moore/post_process/process.py
moore/post_process/coco/__init__.py
moore/post_process/coco/coco_postprocess.py
moore/post_process/coco/test.py
moore/utils/__init__.py
moore/utils/cv_tools.py
moore/utils/general.py
moore/utils/pc_tools.py
moore/visualize/__init__.py
moore/visualize/visual.py
moore/visualize/coco/__init__.py
moore/visualize/coco/visual_coco.py
moore/visualize/labelme/__init__.py
moore/visualize/labelme/visual_labelme.py
moore/visualize/source/__init__.py
moore/visualize/source/visual_source.py
moore/visualize/voc/__init__.py
moore/visualize/voc/visual_voc.py
moore/visualize/yolo/__init__.py
moore/visualize/yolo/visual_yolo.py
Moore_SDK-1.3.0.dist-info/LICENSE
Moore_SDK-1.3.0.dist-info/METADATA
Moore_SDK-1.3.0.dist-info/WHEEL
Moore_SDK-1.3.0.dist-info/top_level.txt
Moore_SDK-1.3.0.dist-info/RECORD
