Metadata-Version: 2.1
Name: Moore_SDK
Version: 1.3.0
Summary: mooreSDK
Author: Xinjun Wu
Author-email: wxj@molardata.com
License-File: LICENSE
Requires-Dist: lxml
Requires-Dist: numpy
Requires-Dist: opencv-python
Requires-Dist: Requests
Requires-Dist: tqdm
Requires-Dist: dynaconf
Requires-Dist: scipy
Requires-Dist: dask[dataframe]
Requires-Dist: python-lzf
Requires-Dist: Pillow
